README.md
setup.py
bigsi/__init__.py
bigsi/__main__.py
bigsi/bitvector.py
bigsi/constants.py
bigsi/decorators.py
bigsi/version.py
bigsi.egg-info/PKG-INFO
bigsi.egg-info/SOURCES.txt
bigsi.egg-info/dependency_links.txt
bigsi.egg-info/entry_points.txt
bigsi.egg-info/requires.txt
bigsi.egg-info/top_level.txt
bigsi/bloom/__init__.py
bigsi/bloom/bloomfilter.py
bigsi/cmds/__init__.py
bigsi/cmds/bloom.py
bigsi/cmds/build.py
bigsi/cmds/delete.py
bigsi/cmds/insert.py
bigsi/cmds/merge.py
bigsi/cmds/samples.py
bigsi/cmds/search.py
bigsi/graph/__init__.py
bigsi/graph/bigsi.py
bigsi/graph/index.py
bigsi/graph/metadata.py
bigsi/matrix/__init__.py
bigsi/matrix/bitmatrix.py
bigsi/matrix/transpose.py
bigsi/scoring/__init__.py
bigsi/scoring/score.py
bigsi/storage/__init__.py
bigsi/storage/base.py
bigsi/storage/berkeleydb.py
bigsi/storage/redis.py
bigsi/storage/rocksdb.py
bigsi/tests/__init__.py
bigsi/tests/base.py
bigsi/tests/scoring.py
bigsi/utils/__init__.py
bigsi/utils/cortex.py
bigsi/utils/fncts.py
bigsi/variants/search.py